{
  "_info": "Mapa de pré-requisitos por curso. Fonte: dados oficiais UFBA/SIGAA. Chave: código da disciplina. Valor: lista de códigos que devem estar aprovados. Disciplinas sem relações de dependência mapeadas não são listadas.",

  "BICTI": {
    "CTIA07": ["CTIA01"],
    "CTIA08": ["CTIA01", "CTIA04"],
    "CTIA09": ["CTIA05"],
    "CTIA11": ["CTIA07"],
    "CTIA23": ["CTIA22"],
    "CTIA25": ["CTIA24"],
    "CTIA28": ["CTIA49"],
    "CTIA29": ["CTIA41"],
    "CTIA31": ["CTIA03"],
    "CTIA33": ["CTIA31"],
    "CTIA34": ["CTIA01", "CTIA28", "CTIA33"],
    "CTIA40": ["CTIA28"],
    "CTIA41": ["CTIA53"],
    "CTIA43": ["CTIA31"],
    "CTIA46": ["CTIA45"],
    "CTIA47": ["CTIA46"],
    "CTIA49": ["CTIA03"],
    "CTIA55": ["CTIA45", "CTIA66"],
    "CTIA56": ["CTIA53"],
    "CTIA58": ["CTIA60"],
    "CTIA60": ["CTIA08"],
    "CTIA66": ["CTIA31"],
    "CTIA72": ["CTIA66"],
    "CTIA73": ["CTIA47"],
    "CTIA74": ["CTIA28", "CTIA66"],
    "CTIA75": ["CTIA78"],
    "CTIA77": ["CTIA45", "CTIA31"],
    "CTIA78": ["CTIA66", "CTIA46"],
    "CTIA84": ["CTIA47"],
    "CTIB07": ["CTIA41"],
    "CTIB10": ["CTIA41", "CTIA72"],
    "CTIB12": ["CTIA41"],
    "CTIB14": ["CTIB13"],
    "CTIB16": ["CTIA41"],
    "CTIB24": ["CTIB21"],
    "CTIB26": ["CTIA33"],
    "GCTI0006": ["GCTI0013"],
    "GCTI0008": ["CTIA03"]
  },

  "ENG_PROD": {
    "CTIA07": ["CTIA01"],
    "CTIA08": ["CTIA01", "CTIA04"],
    "CTIA09": ["CTIA05"],
    "CTIA11": ["CTIA07"],
    "CTIA28": ["CTIA49"],
    "CTIA31": ["CTIA03"],
    "CTIA33": ["CTIA31"],
    "CTIA34": ["CTIA01", "CTIA28", "CTIA33"],
    "CTIA36": ["CTIA45"],
    "CTIA45": ["CTIA31"],
    "CTIA46": ["CTIA45"],
    "CTIA47": ["CTIA46"],
    "CTIA49": ["CTIA03"],
    "CTIA60": ["CTIA08", "CTIA11"],
    "CTIA66": ["CTIA31"],
    "CTIA72": ["CTIA66"],
    "CTIA73": ["CTIA47"],
    "CTIA77": ["CTIA45", "CTIA31"],
    "CTIA78": ["CTIA66", "CTIA46"],
    "CTIA79": ["CTIA03"],
    "CTIA88": ["CTIA72"],
    "CTIA91": ["CTIA86"],
    "CTIA92": ["CTIA89"],
    "CTIA93": ["CTIA85"],
    "CTIA97": ["CTIA88"],
    "CTIA98": ["CTIA91", "CTIA93"],
    "CTIB14": ["CTIB13"],
    "CTIB58": ["CTIA50"],
    "GCTI0001": ["CTIA98"],
    "GCTI0007": ["CTIA98"]
  },

  "ENG_ELET": {
    "CTIA07": ["CTIA01"],
    "CTIA08": ["CTIA01", "CTIA04"],
    "CTIA11": ["CTIA07"],
    "CTIA23": ["CTIA22"],
    "CTIA25": ["CTIA24"],
    "CTIA28": ["CTIA49"],
    "CTIA31": ["CTIA03"],
    "CTIA33": ["CTIA31"],
    "CTIA34": ["CTIA01", "CTIA28", "CTIA33"],
    "CTIA36": ["CTIA45"],
    "CTIA45": ["CTIA31"],
    "CTIA46": ["CTIA45"],
    "CTIA47": ["CTIA46"],
    "CTIA49": ["CTIA31"],
    "CTIA53": ["CTIA01"],
    "CTIA60": ["CTIA08", "CTIA11"],
    "CTIA66": ["CTIA31"],
    "CTIA72": ["CTIA66"],
    "CTIA74": ["CTIA28", "CTIA66"],
    "CTIA77": ["CTIA45", "CTIA31"],
    "CTIA78": ["CTIA66", "CTIA46"],
    "CTIA79": ["CTIA03"],
    "CTIA84": ["CTIA47"],
    "CTIA85": ["CTIA07"],
    "CTIA88": ["CTIA72"],
    "CTIA93": ["CTIA85"],
    "CTIB14": ["CTIB13"],
    "CTIB65": ["CTIA01", "CTIA53"],
    "CTIB66": ["CTIA33", "CTIA74"],
    "CTIB67": ["CTIA36"],
    "CTIB68": ["CTIA33", "CTIA47"],
    "CTIB69": ["CTIA33", "CTIA74"],
    "CTIB70": ["CTIB66"],
    "CTIB71": ["CTIB69"],
    "CTIB72": ["GCTI0013", "CTIB69"],
    "CTIB73": ["CTIB66", "CTIB69"],
    "CTIB74": ["CTIB69"],
    "CTIB75": ["CTIB66", "CTIB73"],
    "CTIB76": ["CTIB71"],
    "CTIB77": ["CTIA01", "CTIB73"],
    "CTIB78": ["CTIA74", "CTIB68", "CTIB76"],
    "CTIB81": ["CTIB74", "CTIB76"],
    "CTIB82": ["CTIB81"],
    "CTIB83": ["CTIB72"],
    "CTIB85": ["CTIA74"],
    "CTIB86": ["CTIB72"],
    "CTIB87": ["CTIB72"],
    "CTIB88": ["CTIA74"],
    "CTIB89": ["CTIB76"],
    "CTIB90": ["CTIB71", "CTIB73"],
    "GCTI0002": ["CTIB74"]
  }
}
